mandoline/__init__.py
mandoline/async_client.py
mandoline/async_connection_manager.py
mandoline/client.py
mandoline/config.py
mandoline/connection_manager.py
mandoline/errors.py
mandoline/logger.py
mandoline/models.py
mandoline/types.py
mandoline/utils.py
mandoline/py.typed
mandoline-0.8.0.dist-info/METADATA
mandoline-0.8.0.dist-info/WHEEL
mandoline-0.8.0.dist-info/licenses/LICENSE
mandoline-0.8.0.dist-info/RECORD
