Metadata-Version: 2.4
Name: mandoline
Version: 0.8.0
Summary: Official Python client for the Mandoline API
Project-URL: Homepage, https://github.com/mandoline-ai/mandoline-python#readme
Project-URL: Repository, https://github.com/mandoline-ai/mandoline-python.git
Author-email: Mandoline AI <support@mandoline.ai>
License: Apache-2.0
License-File: LICENSE
Keywords: ai,api,evaluation,mandoline,metrics
Classifier: Development Status :: 3 - Alpha
Classifier: Intended Audience :: Developers
Classifier: License :: OSI Approved :: Apache Software License
Classifier: Operating System :: OS Independent
Classifier: Programming Language :: Python :: 3
Classifier: Programming Language :: Python :: 3.10
Classifier: Programming Language :: Python :: 3.11
Classifier: Programming Language :: Python :: 3.12
Requires-Python: >=3.10
Requires-Dist: httpx<1,>=0.23.0
Requires-Dist: pydantic<3,>=1.9.0
Provides-Extra: dev
Requires-Dist: hatch>=1.12.0; extra == 'dev'
Requires-Dist: pytest-asyncio>=0.21.0; extra == 'dev'
Requires-Dist: pytest>=8.3.2; extra == 'dev'
Requires-Dist: ruff>=0.7.0; extra == 'dev'
